Workbook

Sheet Summary
A1: Leasium — SMB Property Manager Market Sizing
A2: Target: owners / managers of 2–20 properties. All tenancy figures = dwellings under management (the per-tenant billing unit).
A4: SCENARIO INPUTS (edit the blue cells)
A5: Target market share | B5: 0.5 | C5: ← your assumed capture of each segment
A6: Price per tenant / month (illustrative) | B6: 3 | C6: ← set your own; drives the revenue column only
A8: Country | B8: Segment | C8: Target customers | D8: Segment tenancies (TAM) | E8: Tenancies @ share | F8: Annual revenue @ share
A9: Australia | B9: Self-managing landlords (2–20) | C9: =Australia!B27 -> 194249.4 | D9: =Australia!B28 -> 446440.76 | E9: =D9*$B$5 -> 223220.38 | F9: =E9*$B$6*12 -> 8035933.8
A10: Australia | B10: Small PM agencies | C10: =Australia!B33 -> 11784 | D10: =Australia!B34 -> 2030000 | E10: =D10*$B$5 -> 1015000 | F10: =E10*$B$6*12 -> 36540000
A11: New Zealand | B11: Self-managing landlords (2–20) | C11: ='New Zealand'!B20 -> 43500 | D11: ='New Zealand'!B21 -> 174000 | E11: =D11*$B$5 -> 87000 | F11: =E11*$B$6*12 -> 3132000
A12: New Zealand | B12: Small PM agencies | C12: ='New Zealand'!B26 -> 4000 | D12: ='New Zealand'!B27 -> 300000 | E12: =D12*$B$5 -> 150000 | F12: =E12*$B$6*12 -> 5400000
A13: United States | B13: Self-managing landlords (2–20) | C13: ='United States'!B18 -> 5000000 | D13: ='United States'!B19 -> 11925000 | E13: =D13*$B$5 -> 5962500 | F13: =E13*$B$6*12 -> 214650000
A14: United States | B14: Small PM agencies | C14: ='United States'!B24 -> 238381 | D14: ='United States'!B25 -> 22275000 | E14: =D14*$B$5 -> 11137500 | F14: =E14*$B$6*12 -> 400950000
A15: Notes
A16: • 'Target customers' = number of landlords for self-managing rows; number of PM businesses for agency rows.
A17: • 'Segment tenancies (TAM)' = total dwellings under management in that segment (the whole addressable pool, not your share).
A18: • Self-managing rows count multi-property (2–20) owners only. Agency rows count agent-managed dwellings across all portfolio sizes.
A19: • Australia is the rigorous base case (hard ATO data). New Zealand = medium confidence. United States = order-of-magnitude only.
A20: • See the per-country tabs for the build-up and the 'Sources & Notes' tab for citations, confidence and caveats.

Sheet Targets & Pricing
A1: Leasium — Scaled Targets, Revenue & Pricing
A3: 1. Pricing (per tenant / month)
A4: Private PM — self-managing landlords | B4: 5 | C4: Higher volume / lower touch → lower price
A5: SMB property managers — smaller | B5: 4
A6: SMB property managers — larger | B6: 3
A7: Blended ARPU (base case) | B7: 4 | C7: Editable — mix of private vs agency tenants
A9: 2. Scaled targets (tenants on platform)
B10: Brisbane | C10: SE Queensland | D10: National (AU) | E10: Phase
A11: Target tenants | B11: 5000 | C11: 10000 | D11: 100000 | E11: 1 → 2 → 3
A12: MRR @ blended ($) | B12: =B11*$B$7 -> 20000 | C12: =C11*$B$7 -> 40000 | D12: =D11*$B$7 -> 400000
A13: ARR @ blended ($) | B13: =B11*$B$7*12 -> 240000 | C13: =C11*$B$7*12 -> 480000 | D13: =D11*$B$7*12 -> 4800000
A14: ARR @ $5 (all private) | B14: =B11*$B$4*12 -> 300000 | C14: =C11*$B$4*12 -> 600000 | D14: =D11*$B$4*12 -> 6000000
A15: ARR @ $4 (blended) | B15: =B11*$B$5*12 -> 240000 | C15: =C11*$B$5*12 -> 480000 | D15: =D11*$B$5*12 -> 4800000
A16: ARR @ $3 (all large agency) | B16: =B11*$B$6*12 -> 180000 | C16: =C11*$B$6*12 -> 360000 | D16: =D11*$B$6*12 -> 3600000
A17: Target as % of TOTAL rental market | B17: =B11/'SE Queensland'!B20 -> 0.015827668 | C17: =C11/'SE Queensland'!C20 -> 0.021681737 | D17: =D11/Australia!B17 -> 0.034482759
A18: Target as % of self-managing 2-20 segment | B18: =B11/'SE Queensland'!B25 -> 0.10344881 | C18: =C11/'SE Queensland'!C25 -> 0.1417107 | D18: =D11/Australia!B28 -> 0.22399388
A19: US = Phase 4 (separate model)
A21: 3. Competitor cost reference (effective $/unit/month, small portfolio)
A22: Product | B22: $/unit/mo | C22: Segment / note
A23: Leasium — private landlords | B23: =B4 -> 5 | C23: Self-managing landlords
A24: Leasium — SMB agency (small) | B24: =B5 -> 4 | C24: Small agencies
A25: Leasium — SMB agency (large) | B25: =B6 -> 3 | C25: Larger agencies
A26: RentBetter (AU) | B26: 32 | C26: Self-managing landlord app — $29-36/property
A27: RentingSmart (AU) | B27: 20 | C27: Self-managing landlord app — $15-25/property
A28: PropertyMe (AU) | B28: 8.8 | C28: Agency PM; from $1.76/prop at 100 (≈$8.80 at 20, $176 floor)
A29: DoorLoop (US) | B29: 6.9 | C29: Per-unit w/ plan floor: Starter $69/mo (<=10 units) = $6.90/unit; scales toward ~$3/unit at volume
A30: Buildium (US) | B30: 2.9 | C30: From $58/mo; ~$2.40/unit at 100
A31: Hemlane (US) | B31: 4.33 | C31: $36.50 base + $2.50/unit (at 20 units)
A32: TenantCloud (US) | B32: 2 | C32: From $17/mo; free tier
A33: Re-Leased (commercial) | B33: 18 | C33: Quote-based; ~$18-72/unit at 5-20 units incl. floor+setup
A34: Competitor prices are published list/entry pricing converted to an effective per-unit rate at a small portfolio; AU tools priced per property, US per unit. Re-Leased is quote-based (estimated). Sources on respective sites + Capterra/GetApp.

Sheet SE Queensland
A1: SE Queensland — Brisbane launch → SEQ rollout
A2: Anchored on the RTA's hard bond count (631,805 QLD tenancies, Jun 2025). Brisbane = beachhead; SEQ = the rollout. Segment ratios reuse the Australia tab; maintenance layer added for partner-building.
A4: Assumptions (edit blue cells; green cells link to the Australia tab)
A5: QLD active rental bonds (RTA, 30 Jun 2025) | B5: 631805 | E5: Source: RTA Annual Report 2024-25 (~$1.3B held).
A6: Greater Brisbane share of QLD bonds | B6: 0.5 | E6: Apportionment, anchored to ~48% pop / ~50% rental share. Refine w/ RTA LGA data.
A7: SE Queensland share of QLD bonds | B7: 0.73 | E7: Apportionment, anchored to ~71% pop / higher urban rental share.
A8: Self-management rate | B8: =Australia!B18 -> 0.3 | E8: Linked from Australia tab (30%). QLD may run higher.
A9: Multi-property share of rental dwellings | B9: 0.51 | E9: From ATO: multi-property investors hold ~51% of dwellings.
A10: Avg dwellings per multi-property landlord | B10: =Australia!B25 -> 2.2982865 | E10: Linked from Australia tab (~2.3).
A11: Agent-managed rate | B11: =1-B8 -> 0.7 | E11: Equals 1 minus the self-management rate.
A12: Median weekly rent (SEQ, RTA) | B12: 600 | E12: RTA Q2-2025: Brisbane combined ~$625-700/wk; SEQ blend conservative.
A13: Maintenance as % of annual rent | B13: 0.075 | E13: Industry rule of thumb 5-10% of gross rent.
A14: Maintenance jobs per tenancy / year | B14: 3 | E14: Planning estimate: reactive + periodic jobs per rental/yr.
A15: QLD construction businesses (ABS) | B15: 87000 | E15: ABS Counts of Australian Businesses; QLD construction ~17% of 511,835.
A16: Maintenance-relevant trades share | B16: 0.4 | E16: Est. share of construction firms doing rental maintenance trades.
B18: Greater Brisbane | C18: SE Queensland | D18: Queensland
A19: A. Rental market size (tenancies)
A20: Total rental tenancies (RTA bonds basis) | B20: =$B$5*$B$6 -> 315902.5 | C20: =$B$5*$B$7 -> 461217.65 | D20: =$B$5 -> 631805
A21: Self-managed tenancies (all portfolios) | B21: =B20*$B$8 -> 94770.75 | C21: =C20*$B$8 -> 138365.3 | D21: =D20*$B$8 -> 189541.5
A22: Agent-managed tenancies | B22: =B20*$B$11 -> 221131.75 | C22: =C20*$B$11 -> 322852.35 | D22: =D20*$B$11 -> 442263.5
A23: B. Leasium target segments
A24: Self-managing 2-20 landlords (customers) | B24: =B20*$B$9*$B$8/$B$10 -> 21030.052 | C24: =C20*$B$9*$B$8/$B$10 -> 30703.875 | D24: =D20*$B$9*$B$8/$B$10 -> 42060.103
A25: Self-managing 2-20 tenancies (TAM) | B25: =B20*$B$9*$B$8 -> 48333.082 | C25: =C20*$B$9*$B$8 -> 70566.3 | D25: =D20*$B$9*$B$8 -> 96666.165
A26: Tenancies @ target share (Summary tab) | B26: =B25*Summary!$B$5 -> 24166.541 | C26: =C25*Summary!$B$5 -> 35283.15 | D26: =D25*Summary!$B$5 -> 48333.082 | E26: Uses the market-share input on the Summary tab (default 50%).
A27: Small PM / real estate agencies (count) | B27: 1120 | C27: 1540 | D27: 2110 | E27: Directory counts (rentechdigital). QLD ~2,110; Brisbane ~1,120. Editable.
A28: C. Maintenance partner opportunity
A29: Maintenance jobs / year (whole market) | B29: =B20*$B$14 -> 947707.5 | C29: =C20*$B$14 -> 1383652.9 | D29: =D20*$B$14 -> 1895415 | E29: Total reactive+periodic jobs across all rentals.
A30: Maintenance spend / year (whole market) | B30: =B20*$B$12*52*$B$13 -> 739211850 | C30: =C20*$B$12*52*$B$13 -> 1079249301 | D30: =D20*$B$12*52*$B$13 -> 1478423700 | E30: The rental-maintenance wallet — the prize for partners.
A31: Construction businesses (ABS basis) | B31: =$B$15*$B$6 -> 43500 | C31: =$B$15*$B$7 -> 63510 | D31: =$B$15 -> 87000
A32: Maintenance-relevant trade businesses (est.) | B32: =B31*$B$16 -> 17400 | C32: =C31*$B$16 -> 25404 | D32: =D31*$B$16 -> 34800 | E32: Plumbing, electrical, HVAC, handyman, pest, painting, etc.
A33: Maint. jobs Leasium routes @ target share | B33: =B26*$B$14 -> 72499.624 | C33: =C26*$B$14 -> 105849.45 | D33: =D26*$B$14 -> 144999.25 | E33: Jobs Leasium could route to partners at the Summary share.
A35: Notes & caveats
A36: • Hard anchor = RTA bonds (631,805 QLD tenancies, Jun 2025). Brisbane/SEQ are apportionments of that count — replace shares with RTA postcode/LGA data to firm up.
A37: • Segment ratios (51% multi-property, 30% self-managed, 2.3 dwellings/landlord) are reused from the national Australia tab and link live where possible.
A38: • Maintenance figures are planning estimates: jobs/tenancy/year and % of rent are assumptions, not measured QLD data.
A39: • 'Construction businesses' is ABS-basis (mostly sole-trader tradies); the maintenance-relevant subset is an estimate. Agency counts are directory scrapes.
A40: • For the partner pitch, the headline numbers are the whole-market maintenance wallet and job volume; the 'routes @ share' rows are what Leasium realistically channels early.
A42: Sources: RTA Annual Report 2024-25 (rta.qld.gov.au/annualreport) · profile.id.com.au/comseq (SEQ tenure) · ABS Counts of Australian Businesses / Tradies article (abs.gov.au) · RTA median rents Q2-2025 · rentechdigital agency directory.

Sheet Re-Leased Comparison
A1: Leasium vs Re-Leased — cost & positioning
A2: Re-Leased pricing is QUOTE-BASED (not published). Cells marked ESTIMATE are third-party-derived and editable — drop in a real quote when you have one.
A4: 1. How they differ
B5: Re-Leased | C5: Leasium
A6: Primary segment | B6: Commercial & mixed-use | C6: Residential SMB
A7: Typical portfolio | B7: 50 – 20,000+ leases | C7: 2 – 20 properties
A8: Target buyer | B8: PM firms, commercial landlords, institutions | C8: Self-managing landlords & small agencies
A9: Pricing model | B9: Quote-based, per portfolio (premium) | C9: Transparent per-tenant
A10: Published pricing? | B10: No — request a quote | C10: Yes
A11: Setup / implementation | B11: Mandatory, paid (est. ~40% of yr-1 sub) | C11: Self-serve, $0
A12: Free trial / free tier | B12: No | C12: TBD (low-cost positioning)
A13: Min practical size | B13: ~50 leases | C13: 1+ property
A14: Accounting | B14: Xero / QBO / Sage / NetSuite (2-way) | C14: Xero (review-first)
A15: Signature features | B15: Trust accounting, CAM budgets, Credia AI | C15: Smart Intake, low per-tenant cost
A17: 2. Pricing assumptions (edit the blue cells)
A18: Leasium price per tenant / month | B18: =Summary!B6 -> 3 | C18: linked from the model's Summary tab
A19: Re-Leased est. per unit / month (ESTIMATE) | B19: 3.5 | C19: Third-party est. band ~$1.50–$4/unit; premium commercial
A20: Re-Leased monthly minimum (ESTIMATE) | B20: 150 | C20: Commercial PM platforms typically carry a monthly floor
A21: Re-Leased one-time implementation (ESTIMATE) | B21: 2500 | C21: ITQlick: implementation mandatory, ~40% of yr-1 subscription
A22: Leasium one-time setup | B22: 0 | C22: self-serve onboarding
A24: 3. Annual cost by portfolio size
A25: Portfolio (units) | B25: Leasium / year | C25: Re-Leased / year (ongoing) | D25: Re-Leased year 1 (incl. setup) | E25: Leasium eff. $/unit/mo | F25: Re-Leased eff. $/unit/mo (yr 1)
A26: 5 | B26: =A26*$B$18*12 -> 180 | C26: =MAX(A26*$B$19,$B$20)*12 -> 1800 | D26: =C26+$B$21 -> 4300 | E26: =B26/A26/12 -> 3 | F26: =D26/A26/12 -> 71.666667
A27: 10 | B27: =A27*$B$18*12 -> 360 | C27: =MAX(A27*$B$19,$B$20)*12 -> 1800 | D27: =C27+$B$21 -> 4300 | E27: =B27/A27/12 -> 3 | F27: =D27/A27/12 -> 35.833333
A28: 20 | B28: =A28*$B$18*12 -> 720 | C28: =MAX(A28*$B$19,$B$20)*12 -> 1800 | D28: =C28+$B$21 -> 4300 | E28: =B28/A28/12 -> 3 | F28: =D28/A28/12 -> 17.916667
A29: 50 | B29: =A29*$B$18*12 -> 1800 | C29: =MAX(A29*$B$19,$B$20)*12 -> 2100 | D29: =C29+$B$21 -> 4600 | E29: =B29/A29/12 -> 3 | F29: =D29/A29/12 -> 7.6666667
A30: 100 | B30: =A30*$B$18*12 -> 3600 | C30: =MAX(A30*$B$19,$B$20)*12 -> 4200 | D30: =C30+$B$21 -> 6700 | E30: =B30/A30/12 -> 3 | F30: =D30/A30/12 -> 5.5833333
A31: Note: Re-Leased rarely engages residential portfolios under ~50 units. The 5/10/20 rows show what a small portfolio WOULD pay if accepted — the monthly floor + setup fee dominate at small scale.
A34: 4. Takeaway
A35: • Different buyers: Re-Leased sells to commercial / mid-market property managers; Leasium targets residential SMB self-managers. They rarely meet head-to-head.
A36: • At 2–20 units, Re-Leased's monthly floor + mandatory paid implementation make its effective per-unit cost very high — and it typically won't take a portfolio that small.
A37: • Leasium's wedge is exactly the long tail Re-Leased ignores: transparent, low per-tenant price, $0 setup, self-serve.
A38: • Use Re-Leased as a price ceiling and positioning foil, not a like-for-like competitor. For a true residential head-to-head, benchmark PropertyMe, :Different, Ailo (AU) or DoorLoop/Buildium (US) next.
A39: • Reference point — ITQlick TCO estimate (10 users): ~$3,620/mo + ~$17k implementation ≈ $61k year 1. Illustrates Re-Leased's mid-market price level (estimate, not a quote).

Sheet Australia
A1: Australia — bottom-up market size
A3: 1. Rental property ownership (ATO Taxation Statistics 2021–22)
A4: Investors owning 1 property | B4: 1620633
A5: Investors owning 2 properties | B5: 428020
A6: Investors owning 3 properties | B6: 132338
A7: Investors owning 4 properties | B7: 47633
A8: Investors owning 5 properties | B8: 19530
A9: Investors owning 6+ properties | B9: 19977
A10: Total investors declaring rental income | B10: =SUM(B4:B9) -> 2268131
A11: Multi-property investors (2–20) = target landlord base | B11: =SUM(B5:B9) -> 647498
A12: Single-property investors (adjacent, excluded) | B12: =B4 -> 1620633
A14: 2. Assumptions (edit the blue cells)
A15: Avg properties per '6+' investor | B15: 7.5 | D15: ATO 2019-20 net-rent table: ~19.9k investors hold ~150k interests → ~7.5 avg.
A16: Joint-ownership adj. (interests → dwellings) | B16: 0.88 | D16: Total interests 3.31M vs ~2.9M actual dwellings → 0.88. Removes double-count of jointly-owned properties.
A17: Total private rental dwellings (AU) | B17: 2900000 | D17: ABS/CoreLogic: ~11.2M dwellings; ~26% privately rented → ~2.9M. Flex 2.6-3.1M.
A18: Self-management rate | B18: 0.3 | D18: RentBetter / realestate.com.au / Finder: 25-33% self-manage. Base 30%.
A19: Agent-managed rate | B19: =1-B18 -> 0.7 | D19: Equals 1 minus the self-management rate.
A20: Residential PM businesses (count) | B20: 11784 | D20: IBISWorld: Residential Property Leasing & Management in Australia, 2025 (11,784 businesses).
A22: 3. Dwellings held by the 2–20 segment
A23: Property interests held by multi-property investors | B23: =B5*2+B6*3+B7*4+B8*5+B9*B15 -> 1691063.5
A24: → Dwellings held by multi-property investors | B24: =B23*B16 -> 1488135.9
A25: Avg dwellings per multi-property investor | B25: =B24/B11 -> 2.2982865
A26: 4. Segment A — self-managing landlords (2–20)
A27: Target customers (self-managing multi-prop investors) | B27: =B11*B18 -> 194249.4
A28: Segment tenancies — self-managed, multi-property (TAM) | B28: =B24*B18 -> 446440.76
A29: Customers @ target share | B29: =B27*Summary!B5 -> 97124.7
A30: Tenancies @ target share | B30: =B28*Summary!B5 -> 223220.38
A32: 5. Segment B — small PM agencies
A33: Target customers (residential PM businesses) | B33: =B20 -> 11784
A34: Agent-managed tenancies (TAM) | B34: =B17*B19 -> 2030000
A35: Avg rent roll per agency (doors) | B35: =B34/B20 -> 172.26748
A36: Businesses @ target share | B36: =B33*Summary!B5 -> 5892
A37: Tenancies @ target share | B37: =B34*Summary!B5 -> 1015000
A39: Reconciliation: Seg A self-mgd (multi) + single-prop self-mgd + agent-managed ≈ total rental dwellings
A40: Single-property self-managed (adjacent pool, excluded from 2–20) | B40: =B12*B16*B18 -> 427847.11

Sheet New Zealand
A1: New Zealand — market size (medium confidence)
A3: Assumptions (edit the blue cells)
A4: Total rental dwellings (NZ) | B4: 600000 | D4: StatsNZ ~600k renting households (Census). Active bonds Nov-2024 = 410,904 as a conservative floor.
A5: Share of landlords owning only 1 property | B5: 0.8 | D5: Stuff/MBIE: ~80% of NZ landlords own a single property.
A6: Multi-property share of dwellings | B6: 0.5 | D6: Assumed: multi-property landlords hold ~half of dwellings (mirrors AU skew).
A7: Self-management rate | B7: 0.58 | D7: MBIE: PMs manage ~42% of rentals → ~58% self-managed.
A8: Agent-managed rate | B8: =1-B6 -> 0.5 | D8: Equals 1 minus the self-management rate.
A9: Residential property managers (count) | B9: 4000 | D9: MBIE 2022 discussion paper: estimated 2,096–7,881 residential PMs. Midpoint used.
A11: Derived landlord & dwelling counts
A12: Single-property dwellings (= single-prop landlords) | B12: =B4*(1-B6) -> 300000
A13: Total landlords | B13: =B12/B5 -> 375000
A14: Multi-property landlords (2–20) | B14: =B13*(1-B5) -> 75000
A15: Dwellings held by multi-property landlords | B15: =B4*B6 -> 300000
A17: Segment A — self-managing landlords (2–20)
A18: Target customers (self-managing multi-prop landlords) | B18: =B14*B7 -> 43500
A19: Segment tenancies — self-managed, multi-property (TAM) | B19: =B15*B7 -> 174000
A20: Target customers (link target) | B20: =B18 -> 43500
A21: Segment tenancies (link target) | B21: =B19 -> 174000
A23: Segment B — small PM agencies
A24: Target customers (residential PMs) | B24: =B9 -> 4000
A25: Agent-managed tenancies (TAM) | B25: =B4*B8 -> 300000
A26: Target customers (link target) | B26: =B24 -> 4000
A27: Segment tenancies (link target) | B27: =B25 -> 300000

Sheet United States
A1: United States — scale estimate (order-of-magnitude)
A3: Assumptions (edit the blue cells)
A4: Total rental units (US) | B4: 49500000 | D4: HUD/Census Rental Housing Finance Survey: ~49.5M rental units.
A5: Individual investor landlords | B5: 10500000 | D5: Multiple sources: 10-11M individual ('mom & pop') landlords.
A6: Individually-owned 1–4 unit dwellings | B6: 15900000 | D6: RHFS: individuals own ~70% of 1-4 unit stock = ~15.9M units.
A7: Individual landlords owning 2–20 units | B7: 5000000 | D7: Estimate: ~half of individual landlords own 2+ units. Rough.
A8: Self-management rate (small landlords) | B8: 0.75 | D8: Small US landlords largely self-manage; ~70-80%. Base 75%.
A9: Agent/professionally-managed share of units | B9: 0.45 | D9: Low-confidence estimate of professionally managed share of all units.
A10: Residential property managers (businesses) | B10: 238381 | D10: IBISWorld: Residential Property Managers in the US, 2024 (238,381).
A13: Segment A — self-managing landlords (2–20)
A14: Target customers (2–20 unit individual landlords) | B14: =B7 -> 5000000
A15: Segment tenancies — self-managed small-property units (TAM) | B15: =B6*B8 -> 11925000 | D15: Approx: individually-owned 1-4 unit dwellings × self-mgmt rate. Includes single-unit; the 2-20 subset is the bulk.
A16: Note: rows 18/19 & 24/25 are the Summary link targets.
A18: Target customers (link target) | B18: =B14 -> 5000000
A19: Segment tenancies (link target) | B19: =B15 -> 11925000
A21: Segment B — small PM agencies
A22: Target customers (residential PM businesses) | B22: =B10 -> 238381
A23: Professionally-managed units (TAM) | B23: =B4*B9 -> 22275000
A24: Target customers (link target) | B24: =B22 -> 238381
A25: Segment tenancies (link target) | B25: =B23 -> 22275000

Sheet Sources & Notes
A1: Sources, methodology & confidence
A3: METHOD
A4: Tenancy = one dwelling under management = the per-tenant billing unit. We size each segment's total dwellings (TAM), then apply your target market-share input on the Summary tab.
A5: Two segments per country: (A) self-managing landlords who own 2–20 properties; (B) small property-management agencies. They do not overlap (a dwelling is either self-managed or agent-managed).
A7: CONFIDENCE
A8: Australia — HIGH. Built from ATO tax data (every landlord who declares rental income) plus IBISWorld business counts.
A9: New Zealand — MEDIUM. Bond/Census dwelling counts are solid; landlord split and PM count are estimated from MBIE ranges.
A10: United States — LOW / order-of-magnitude. Huge, fragmented market; the 2–20 individual-landlord count is a rough estimate and 50% capture is purely illustrative.
A12: KEY CAVEATS
A13: • ATO counts 'property interests' not dwellings — a couple owning one property = two interests. We apply a 0.88 factor (3.31M interests ≈ 2.9M dwellings) to avoid double-counting.
A14: • 'Small PM agency' as literally 2–20 doors is a tiny new-entrant niche; almost all agencies run larger rent rolls (~172 doors avg in AU). The agency rows therefore size SMB agencies broadly, priced per managed door.
A15: • Self-management rate is the single most sensitive lever for Segment A — it ranges 25–33% (AU). Flex it on each country tab.
... A29: Harvard JCHS / Urban Institute — mom-and-pop landlord share of US rental stock — jchs.harvard.edu, urban.org
